walleot-0.4.3.dist-info/METADATA
walleot-0.4.3.dist-info/WHEEL
walleot-0.4.3.dist-info/entry_points.txt
walleot/__init__.py
walleot/core.py
walleot-0.4.3.dist-info/RECORD
