Metadata-Version: 2.1
Name: walleot
Version: 0.4.3
Summary: Payment support for MCP-based tools and agents.
Author-Email: Blust Inc <info@blust.ai>
License: MIT
Requires-Python: >=3.10
Requires-Dist: paymcp>=0.4.3
